{
  "db_name": "PostgreSQL",
  "query": "SELECT m.msg_id as \"msg_id!\", COUNT(cr.user_id) as \"read!: i64\",\n                  ((SELECT COUNT(*) FROM im_group_members WHERE group_id = $1) - 1) as \"total!: i64\"\n           FROM unnest($2::bigint[]) AS m(msg_id)\n           JOIN im_group_messages gm ON gm.id = m.msg_id\n           LEFT JOIN im_group_read_cursors cr ON cr.group_id = $1\n                  AND cr.last_read_msg_id >= m.msg_id\n                  AND cr.user_id != gm.from_uid\n           GROUP BY m.msg_id",
  "describe": {
    "columns": [
      {
        "ordinal": 0,
        "name": "msg_id!",
        "type_info": "Int8"
      },
      {
        "ordinal": 1,
        "name": "read!: i64",
        "type_info": "Int8"
      },
      {
        "ordinal": 2,
        "name": "total!: i64",
        "type_info": "Int8"
      }
    ],
    "parameters": {
      "Left": [
        "Uuid",
        "Int8Array"
      ]
    },
    "nullable": [
      null,
      null,
      null
    ]
  },
  "hash": "b66ebd0e57d3f51ded4de2ec55fc71f632fe667e260f486813a4e6e06eb42a55"
}
